{"agents":[{"id":"echo-xrpl","txCount":4255,"successRate":"97.7%","totalSpent":"21.17","agentId":"echo-xrpl","today":0.46170000000000005,"dailyLimit":100,"remaining":99.5383},{"id":"atlas-arb","txCount":6451,"successRate":"98.0%","totalSpent":"31.35","agentId":"atlas-arb","today":3.4911999999999948,"dailyLimit":100,"remaining":96.50880000000001},{"id":"atlas-xrpl","txCount":3282,"successRate":"97.8%","totalSpent":"16.42","agentId":"atlas-xrpl","today":0.44759999999999994,"dailyLimit":100,"remaining":99.5524},{"id":"nova-xrpl","txCount":3770,"successRate":"98.0%","totalSpent":"18.75","agentId":"nova-xrpl","today":0.5231999999999999,"dailyLimit":100,"remaining":99.4768},{"id":"pixel-arb","txCount":4420,"successRate":"97.6%","totalSpent":"21.75","agentId":"pixel-arb","today":2.1395000000000004,"dailyLimit":100,"remaining":97.8605},{"id":"nova-arb","txCount":5148,"successRate":"98.2%","totalSpent":"25.32","agentId":"nova-arb","today":2.7274,"dailyLimit":100,"remaining":97.2726},{"id":"echo-arb","txCount":4618,"successRate":"98.1%","totalSpent":"22.71","agentId":"echo-arb","today":2.974000000000005,"dailyLimit":100,"remaining":97.026},{"id":"pixel-xrpl","txCount":3968,"successRate":"98.1%","totalSpent":"19.84","agentId":"pixel-xrpl","today":0.34879999999999994,"dailyLimit":100,"remaining":99.6512}],"totalAgents":8,"totalTxs":35912,"verified":35178,"chains":["arbitrum","xrplEvm"]}